[
  {
    "term": "Acústica del cosmos",
    "definition": "Concepto que refiere a las resonancias naturales y cósmicas que preceden la música formalizada."
  },
  {
    "term": "Performatividad extrema",
    "definition": "Prácticas performativas que empujan los límites del cuerpo, la técnica y la representación."
  },
  {
    "term": "Genealogías feministas del ruido",
    "definition": "Historia y desarrollo de prácticas sonoras ruidistas desde perspectivas feministas y críticas."
  },
  {
    "term": "Biología expandida",
    "definition": "Intersección entre prácticas sonoras y biotecnologías o procesos biológicos."
  },
  {
    "term": "Cosmología del fin",
    "definition": "Narrativas estéticas sobre el cierre del tiempo y el sonido asociado a ese horizonte."
  }
]